torchfuzzy/__init__.py
torchfuzzy/defuzzy_linear.py
torchfuzzy/fuzzy_bell_layer.py
torchfuzzy/fuzzy_layer.py
torchfuzzy-0.0.2.dist-info/LICENSE
torchfuzzy-0.0.2.dist-info/METADATA
torchfuzzy-0.0.2.dist-info/WHEEL
torchfuzzy-0.0.2.dist-info/top_level.txt
torchfuzzy-0.0.2.dist-info/RECORD
